{
    "id": 10274,
    "name": "Meteor",
    "domains": [
        {
            "id": 256,
            "name": "Corporate Systems & Finance"
        },
        {
            "id": 12908,
            "name": "PE Firm"
        }
    ],
    "metrics": [
        {
            "snapshotLabel": "TrendCampaign_4_Meteor",
            "snapshotDate": 1488171600000,
            "softwareAgility": 0.7593119144439697,
            "softwareAgilityAdded": 0.7593119144439697,
            "softwareElegance": 0.5591579675674438,
            "softwareEleganceAdded": 0.5591579675674438,
            "softwareResiliency": 0.6035659313201904,
            "softwareResiliencyAdded": 0.6035659313201904,
            "softwareHealth": 0.640678604443868,
            "openSourceSafety": 1.0,
            "openSourceLicense": 1.0,
            "openSourceObsolescence": null,
            "openSourceCVE": 1.0,
            "businessImpact": 0.4517766497461929,
            "roarIndex": 0.1760759126142132,
            "backFiredFP": 172.0,
            "backFiredFPAdded": 172.0,
            "technicalDebt": 20804.709015130997,
            "maintenanceRecordedFTE": 1.2,
            "maintenanceRecommendedFTE": 0.0,
            "greenIndex": null,
            "greenIndexScan": null,
            "greenIndexSurvey": null,
            "greenOccurrences": null,
            "greenEffort": null,
            "greenDetail": [
                {
                    "technology": "JavaScript",
                    "greenIndexScan": 0.0,
                    "greenIndexDetails": null
                }
            ],
            "totalLinesOfCode": 9140,
            "totalLinesOfCodeAdded": 9140,
            "totalLinesOfCodeModified": 0,
            "totalFiles": 86,
            "totalFilesAdded": 86,
            "totalFilesModified": 0,
            "customIndicators": [
                {
                    "metricId": 10023356,
                    "value": "0.10101010101010101"
                },
                {
                    "metricId": 10006001,
                    "value": "0.5277777777777778"
                },
                {
                    "metricId": 10006305,
                    "value": "-1.0"
                },
                {
                    "metricId": 10013600,
                    "value": "-1.0"
                },
                {
                    "metricId": 10006302,
                    "value": "-1.0"
                },
                {
                    "metricId": 10006301,
                    "value": "-1.0"
                },
                {
                    "metricId": 10016304,
                    "value": "-1.0"
                }
            ],
            "technologies": [
                {
                    "technology": "JavaScript",
                    "totalLinesOfCode": 9140,
                    "totalFiles": 86,
                    "softwareAgility": 0.7593119144439697,
                    "softwareElegance": 0.5591579675674438,
                    "softwareResiliency": 0.6035659313201904,
                    "softwareHealth": 0.640678604443868,
                    "softwareAgilityDetail": {
                        "highLinesOfCode": 3809,
                        "mediumLinesOfCode": 4751,
                        "lowLinesOfCode": 580
                    },
                    "softwareEleganceDetail": {
                        "highLinesOfCode": 370,
                        "mediumLinesOfCode": 5474,
                        "lowLinesOfCode": 3296
                    },
                    "softwareResiliencyDetail": {
                        "highLinesOfCode": 2106,
                        "mediumLinesOfCode": 3801,
                        "lowLinesOfCode": 3233
                    },
                    "softwareHealthDetail": {
                        "highLinesOfCode": 2095,
                        "mediumLinesOfCode": 4675,
                        "lowLinesOfCode": 2369
                    }
                }
            ],
            "components": []
        }
    ],
    "surveys": [
        {
            "id": 371,
            "ref": "CAST_MAINT",
            "name": "Software Maintenance Estimate",
            "questions": [
                {
                    "label": "What is the average skill level of the development team on this type of application?",
                    "value": "1 year",
                    "questionId": 1000015,
                    "choiceId": 1000068
                },
                {
                    "label": "What percentage of the development effort has been spent on maintenance in the last 12 months?",
                    "value": "30",
                    "questionId": 1000012
                },
                {
                    "label": "What is the CMMI level of the organization?",
                    "value": "Level 1 (upper half)",
                    "questionId": 1000032,
                    "choiceId": 1000255
                },
                {
                    "label": "What is the percentage of change to the base code in the last 12 months?",
                    "value": "5",
                    "questionId": 1000121
                },
                {
                    "label": "What is the annual staff turnover within the development team?",
                    "value": "10%",
                    "questionId": 1000016,
                    "choiceId": 1000143
                }
            ]
        },
        {
            "id": 4,
            "ref": "CAST_BI",
            "name": "Business Impact",
            "questions": [
                {
                    "label": "What is the average number of FTE (Full Time Equivalent) resources that have worked on the source code for this application over the last 12 months?",
                    "shortLabel": "",
                    "value": "4",
                    "questionId": 1000011
                },
                {
                    "label": "Is this application aligned with the company's future technology direction?",
                    "shortLabel": "",
                    "value": "Yes",
                    "questionId": 1000009,
                    "choiceId": 1000042
                },
                {
                    "label": "The number of major releases delivered over the last 12 months for this application?",
                    "shortLabel": "",
                    "value": "7 to 12",
                    "questionId": 1000006,
                    "choiceId": 1000454
                },
                {
                    "label": "Could failure of this application lead to loss of customer confidence? Please define the level of impact.",
                    "value": "Medium",
                    "questionId": 1000022,
                    "choiceId": 1000221
                },
                {
                    "label": "Could failure of this application lead to harm of the company's public image? Please define the level of impact.",
                    "value": "Very High",
                    "questionId": 1000021,
                    "choiceId": 1000003
                },
                {
                    "label": "Could failure of this application lead to loss of revenue or business opportunity? Please define the level of impact.",
                    "value": "High",
                    "questionId": 1000020,
                    "choiceId": 1000408
                },
                {
                    "label": "Could failure of this application lead to disruption? Please define the level of impact.",
                    "value": "High",
                    "questionId": 1000019,
                    "choiceId": 1000194
                },
                {
                    "label": "What is the approximate number of end users for this application?",
                    "shortLabel": "",
                    "value": "100 to 500",
                    "questionId": 1000018,
                    "choiceId": 1000396
                },
                {
                    "label": "Does the application serve internal or external users?",
                    "value": "Internal users or business processes",
                    "questionId": 1000017,
                    "choiceId": 1000204
                }
            ]
        },
        {
            "id": 373,
            "ref": "CAST_APP",
            "name": "Application Properties",
            "questions": [
                {
                    "label": "Is this application a custom application or a Commercial Off The Shelf product?",
                    "shortLabel": "",
                    "value": "Custom Application",
                    "questionId": 1000427,
                    "choiceId": 1000529
                },
                {
                    "label": "What is the application type?",
                    "shortLabel": "",
                    "value": "Asset Management Operations / Technology",
                    "questionId": 1000004,
                    "choiceId": 1000425
                },
                {
                    "label": "Application Owner's name",
                    "value": "Michael MULLER",
                    "questionId": 1000002
                },
                {
                    "label": "In what year was this application first put into production?",
                    "shortLabel": "",
                    "value": "2010",
                    "questionId": 1000033
                }
            ]
        }
    ]
}